laravalidation
