Metadata-Version: 2.1
Name: laravalidation
Version: 0.4.1
Summary: Laravel like data validation library for python language
Home-page: https://github.com/kristopherchun/laravalidation.git
Author: Walid Mashal
Author-email: walidmashal4@gmail.com
License: UNKNOWN
Keywords: validation,python,laravel
Platform: UNKNOWN
